Metadata-Version: 1.1
Name: imtools
Version: 1.5.1
Summary: 3D data processing toolbox
Home-page: https://github.com/mjirik/imtools
Author: Miroslav Jirik and Tomas Ryba
Author-email: miroslav.jirik@gmail.com
License: MIT
Keywords: dicom,3D,tools,image processing
Platform: UNKNOWN
Classifier: Development Status :: 3 - Alpha
Classifier: Intended Audience :: Developers
Classifier: Topic :: Scientific/Engineering :: Bio-Informatics
Classifier: License :: OSI Approved :: BSD License
Classifier: Programming Language :: Python :: 2.7
Classifier: Programming Language :: Python :: 3.6
